{"users":[{"id":"d20be3ac-bacb-5fe7-ae45-268495962ead","firstName":"Jaden","lastName":"Reichel","country":"Sri Lanka","createdAt":"2017-01-24T20:40:42.712Z","email":"Hosea39@yahoo.com"},{"id":"ad84b586-4ee7-575e-9606-ef095a4ab62e","firstName":"Gabe","lastName":"Douglas","country":"Germany","createdAt":"2016-12-20T07:44:26.720Z","email":"Federico40@gmail.com"},{"id":"892fe909-cab9-52b1-a66f-5849b0d83842","firstName":"Alayna","lastName":"Wuckert","country":"Anguilla","createdAt":"2017-04-27T16:17:45.345Z","email":"Wilhelm66@gmail.com"}]}